README.rst
setup.py
spellbook.egg-info/PKG-INFO
spellbook.egg-info/SOURCES.txt
spellbook.egg-info/dependency_links.txt
spellbook.egg-info/entry_points.txt
spellbook.egg-info/requires.txt
spellbook.egg-info/top_level.txt
spellbooker/__init__.py
spellbooker/application.py