Metadata-Version: 1.1
Name: spellbook
Version: 1.1.5
Summary: store and search command lines
Home-page: https://github.com/donpiekarz/spellbook
Author: Bartlomiej Piekarski
Author-email: bartlomiej.piekarski@gmail.com
License: BSD
Download-URL: https://github.com/donpiekarz/spellbook/tarball/1.1.5
Platform: UNKNOWN
Classifier: Development Status :: 3 - Alpha
Classifier: Intended Audience :: Developers
Classifier: Intended Audience :: System Administrators
Classifier: Intended Audience :: End Users/Desktop
Classifier: Intended Audience :: Science/Research
Classifier: Topic :: System :: Shells
Classifier: Topic :: System :: System Shells
Classifier: License :: OSI Approved :: BSD License
Classifier: Programming Language :: Python :: 2
Classifier: Programming Language :: Python :: 2.6
Classifier: Programming Language :: Python :: 2.7
Classifier: Programming Language :: Python :: 3
Classifier: Programming Language :: Python :: 3.2
Classifier: Programming Language :: Python :: 3.3
Classifier: Programming Language :: Python :: 3.4
Classifier: Programming Language :: Python :: 3.5
